datasette_media/__init__.py
datasette_media/utils.py
datasette_media-0.5.1.dist-info/LICENSE
datasette_media-0.5.1.dist-info/METADATA
datasette_media-0.5.1.dist-info/WHEEL
datasette_media-0.5.1.dist-info/entry_points.txt
datasette_media-0.5.1.dist-info/top_level.txt
datasette_media-0.5.1.dist-info/RECORD
