Metadata-Version: 2.1
Name: datasette-media
Version: 0.5.1
Summary: Datasette plugin for serving media based on a SQL query
Home-page: https://github.com/simonw/datasette-media
Author: Simon Willison
License: Apache License, Version 2.0
Project-URL: Issues, https://github.com/simonw/datasette-media/issues
Project-URL: CI, https://github.com/simonw/datasette-media/actions
Project-URL: Changelog, https://github.com/simonw/datasette-media/releases
Classifier: Framework :: Datasette
Classifier: License :: OSI Approved :: Apache Software License
License-File: LICENSE
Requires-Dist: datasette (>=0.44)
Requires-Dist: Pillow (>=7.1.2)
Requires-Dist: httpx (>=0.13.3)
Provides-Extra: heif
Requires-Dist: pyheif (>=0.4) ; extra == 'heif'
Provides-Extra: test
Requires-Dist: asgiref ; extra == 'test'
Requires-Dist: pytest ; extra == 'test'
Requires-Dist: pytest-asyncio ; extra == 'test'
Requires-Dist: sqlite-utils ; extra == 'test'
Requires-Dist: pytest-httpx (>=0.4.0) ; extra == 'test'
